plagiarism_detect_for_nju/__init__.py
plagiarism_detect_for_nju/detect_from_logfile_batch.py
plagiarism_detect_for_nju-1.0.4.dist-info/METADATA
plagiarism_detect_for_nju-1.0.4.dist-info/WHEEL
plagiarism_detect_for_nju-1.0.4.dist-info/entry_points.txt
plagiarism_detect_for_nju-1.0.4.dist-info/licenses/LICENSE
plagiarism_detect_for_nju-1.0.4.dist-info/RECORD
