Metadata-Version: 2.3
Name: plagiarism_detect_for_nju
Version: 1.0.4
Summary: Plagiarism detection tool for C Programming Language course in Nanjing University using HUSTOJ as Online Judge. Makes my life easier.
Author-email: UshioA <shiosshio@outlook.com>
License:                    GNU LESSER GENERAL PUBLIC LICENSE
License-File: LICENSE
Keywords: plagiarism
Classifier: License :: OSI Approved :: GNU Lesser General Public License v3 (LGPLv3)
Classifier: Operating System :: OS Independent
Classifier: Programming Language :: Python :: 3
Requires-Python: >=3.6
